jiesu_service/__init__.py
jiesu_service/service.py
jiesu_service-1.22.dist-info/METADATA
jiesu_service-1.22.dist-info/WHEEL
jiesu_service-1.22.dist-info/top_level.txt
jiesu_service-1.22.dist-info/RECORD
