Metadata-Version: 2.4
Name: jiesu_service
Version: 1.22
Summary: A Python Service
Author: Jie Su
Requires-Python: >=3.6
Requires-Dist: requests
Requires-Dist: py-eureka-client
